{
  "provider": "PixelLab MCP v3",
  "status": "completed_and_reviewed",
  "character_id": "54985209-48f1-4d6f-9d82-f6b6a92323dd",
  "biological_manifest": "../../../../../tools/pixellab-first10-combat-manifest.json#volcazote",
  "directions": { "front": "south", "back": "north" },
  "frame_count": 8,
  "idle_frame_ms": 120,
  "attack_frame_ms": 90,
  "animation_jobs": {
    "idle": { "front": "a125e22a-ae17-4c04-bd59-d996890886fd", "back": "b0534d48-acd3-4285-b055-fae976949d56" },
    "melee": { "front": "9ae768b8-1074-4adb-b252-8a6d45a4b9e7", "back": "fd3995f3-a36a-4f41-974f-6a55b8aaf7f9" },
    "ranged": { "front": "4646263c-2e59-4597-8aff-eee785086444", "back": "4932dba0-7e84-479a-b86d-dee168917791" }
  },
  "selected_frames": {
    "idle_front": [0, 1, 2, 3, 4, 5, 6, 7],
    "idle_back": [0, 0, 0, 0, 0, 0, 0, 0],
    "melee_front": [0, 1, 2, 3, 4, 5, 6, 7],
    "melee_back": [0, 1, 4, 5, 6, 7, 7, 7],
    "ranged_front": [0, 1, 2, 3, 4, 5, 6, 7],
    "ranged_back": [0, 1, 2, 3, 4, 5, 6, 7]
  },
  "review": "The volcanic body remains planted. Claws drive the melee strike and shell fissures drive the ranged eruption. Rear-idle morphs and the ambiguous middle of the first rear claw pass were excluded."
}
